dfpeek/__main__.py
dfpeek-0.1.8.dist-info/METADATA
dfpeek-0.1.8.dist-info/WHEEL
dfpeek-0.1.8.dist-info/entry_points.txt
dfpeek-0.1.8.dist-info/top_level.txt
dfpeek-0.1.8.dist-info/RECORD
